django_security_keys/__init__.py
django_security_keys/admin.py
django_security_keys/apps.py
django_security_keys/backends.py
django_security_keys/ext/__init__.py
django_security_keys/ext/two_factor/__init__.py
django_security_keys/ext/two_factor/forms.py
django_security_keys/ext/two_factor/views.py
django_security_keys/forms.py
django_security_keys/migrations/0001_initial.py
django_security_keys/migrations/0002_attestation.py
django_security_keys/migrations/0003_date_fields.py
django_security_keys/migrations/__init__.py
django_security_keys/models.py
django_security_keys/static/base64/base64url-arraybuffer.js
django_security_keys/static/django-security-keys/django-security-keys.js
django_security_keys/templates/django-security-keys/base.html
django_security_keys/templates/django-security-keys/init.html
django_security_keys/templates/django-security-keys/login.html
django_security_keys/templates/django-security-keys/manage-keys.html
django_security_keys/templates/django-security-keys/static-includes.html
django_security_keys/templatetags/__init__.py
django_security_keys/templatetags/two_factor_ext.py
django_security_keys/tests.py
django_security_keys/urls.py
django_security_keys/views.py
django_security_keys-1.1.0.dist-info/entry_points.txt
django_security_keys-1.1.0.dist-info/WHEEL
django_security_keys-1.1.0.dist-info/METADATA
django_security_keys-1.1.0.dist-info/RECORD
