Metadata-Version: 2.1
Name: django-security-keys
Version: 1.1.0
Summary: Django webauthn security key integration
Home-page: https://github.com/fullctl/django-security-keys
License: Apache-2
Author: 20C
Author-email: code@20c.com
Requires-Python: >=3.8,<4.0
Classifier: Development Status :: 5 - Production/Stable
Classifier: License :: OSI Approved :: Apache Software License
Classifier: License :: Other/Proprietary License
Classifier: Programming Language :: Python :: 3
Classifier: Programming Language :: Python :: 3.10
Classifier: Programming Language :: Python :: 3.11
Classifier: Programming Language :: Python :: 3.8
Classifier: Programming Language :: Python :: 3.9
Classifier: Topic :: Software Development
Requires-Dist: django-two-factor-auth (>=1.13.1,<2.0.0)
Requires-Dist: phonenumbers (>=8.12.47,<9.0.0)
Requires-Dist: webauthn (>=1,<2)
Project-URL: Repository, https://github.com/fullctl/django-security-keys
